{
  "_meta": {
    "produced_by": "analysis/model_selection.py",
    "produced_at_pt": "2026-07-18T10:20:30-07:00",
    "dispatcher_git_sha": "f8c9e9ecc117fcc0f8501f8ef1f331c49f15104f",
    "wrapper_git_sha": null,
    "wandb_groups": [
      "updnet-ratio-100mice@20260703-200122",
      "mult-beta-d614@20260713-003501"
    ]
  },
  "note": "axes = in-sample (training mice) vs held-out (unseen mice) NormLik; the population-transfer analog of Kevin's within-subject odd/even plot. gap = in - heldout > 0 means the penalty overfits the training cohort. Both D panels are lr=1e-3 (study 03's lr=1e-3 slice via pull_selection_data.py).",
  "per_D_beta_centroid": [
    {
      "D": 100,
      "beta": 0.0003,
      "heldout_ll": 0.717,
      "in_ll": 0.7197,
      "gap": 0.0027,
      "n": 9
    },
    {
      "D": 100,
      "beta": 0.001,
      "heldout_ll": 0.717,
      "in_ll": 0.7168,
      "gap": -0.0002,
      "n": 10
    },
    {
      "D": 100,
      "beta": 0.003,
      "heldout_ll": 0.7107,
      "in_ll": 0.7097,
      "gap": -0.0009,
      "n": 10
    },
    {
      "D": 614,
      "beta": 0.0003,
      "heldout_ll": 0.7186,
      "in_ll": 0.7269,
      "gap": 0.0083,
      "n": 4
    },
    {
      "D": 614,
      "beta": 0.001,
      "heldout_ll": 0.7169,
      "in_ll": 0.724,
      "gap": 0.007,
      "n": 4
    },
    {
      "D": 614,
      "beta": 0.003,
      "heldout_ll": 0.7102,
      "in_ll": 0.7146,
      "gap": 0.0043,
      "n": 4
    }
  ]
}